{"asks":[{"side":"ask","price":{"amount":"0.705500","currency_code":"USD"},"quantity":100},{"side":"ask","price":{"amount":"0.708500","currency_code":"USD"},"quantity":100}],"bids":[{"side":"bid","price":{"amount":"0.456000","currency_code":"USD"},"quantity":1000},{"side":"bid","price":{"amount":"0.440400","currency_code":"USD"},"quantity":3000},{"side":"bid","price":{"amount":"0.417100","currency_code":"USD"},"quantity":100},{"side":"bid","price":{"amount":"0.415000","currency_code":"USD"},"quantity":100}],"instrument_id":"d3d644ec-600a-4472-b0cf-d4fb4ab5aac1","updated_at":"2023-01-05T19:15:37.229332584-05:00"}