{"asks":[{"side":"ask","price":{"amount":"4.550000","currency_code":"USD"},"quantity":100},{"side":"ask","price":{"amount":"4.880000","currency_code":"USD"},"quantity":100},{"side":"ask","price":{"amount":"4.900000","currency_code":"USD"},"quantity":100}],"bids":[{"side":"bid","price":{"amount":"4.280000","currency_code":"USD"},"quantity":20},{"side":"bid","price":{"amount":"4.210000","currency_code":"USD"},"quantity":600},{"side":"bid","price":{"amount":"4.200000","currency_code":"USD"},"quantity":223},{"side":"bid","price":{"amount":"4.020000","currency_code":"USD"},"quantity":100},{"side":"bid","price":{"amount":"4.000000","currency_code":"USD"},"quantity":100},{"side":"bid","price":{"amount":"3.940000","currency_code":"USD"},"quantity":10},{"side":"bid","price":{"amount":"3.410000","currency_code":"USD"},"quantity":15}],"instrument_id":"de0cf877-dab6-4f53-a3c7-4524b7ac3af8","updated_at":"2023-01-05T19:16:48.743544855-05:00"}