{"asks":[{"side":"ask","price":{"amount":"60.730000","currency_code":"USD"},"quantity":55},{"side":"ask","price":{"amount":"93.560000","currency_code":"USD"},"quantity":200}],"bids":[{"side":"bid","price":{"amount":"56.890000","currency_code":"USD"},"quantity":5},{"side":"bid","price":{"amount":"55.370000","currency_code":"USD"},"quantity":50},{"side":"bid","price":{"amount":"23.400000","currency_code":"USD"},"quantity":200}],"instrument_id":"915a74d8-a7af-4e1a-b695-02b1d3100a59","updated_at":"2023-01-05T19:15:27.721288377-05:00"}