{"asks":[{"side":"ask","price":{"amount":"18.460000","currency_code":"USD"},"quantity":100},{"side":"ask","price":{"amount":"18.540000","currency_code":"USD"},"quantity":100}],"bids":[{"side":"bid","price":{"amount":"15.090000","currency_code":"USD"},"quantity":500},{"side":"bid","price":{"amount":"14.650000","currency_code":"USD"},"quantity":7},{"side":"bid","price":{"amount":"14.500000","currency_code":"USD"},"quantity":2},{"side":"bid","price":{"amount":"14.400000","currency_code":"USD"},"quantity":5},{"side":"bid","price":{"amount":"13.800000","currency_code":"USD"},"quantity":100},{"side":"bid","price":{"amount":"13.740000","currency_code":"USD"},"quantity":100}],"instrument_id":"57c8d8bc-7236-4490-beb8-9e5f20fe4d8a","updated_at":"2023-01-05T19:13:02.583122831-05:00"}