{"asks":[{"side":"ask","price":{"amount":"1.820000","currency_code":"USD"},"quantity":100},{"side":"ask","price":{"amount":"1.830000","currency_code":"USD"},"quantity":100},{"side":"ask","price":{"amount":"44.440000","currency_code":"USD"},"quantity":1000}],"bids":[{"side":"bid","price":{"amount":"1.630000","currency_code":"USD"},"quantity":10},{"side":"bid","price":{"amount":"1.600000","currency_code":"USD"},"quantity":809},{"side":"bid","price":{"amount":"1.590000","currency_code":"USD"},"quantity":6},{"side":"bid","price":{"amount":"1.580000","currency_code":"USD"},"quantity":6},{"side":"bid","price":{"amount":"1.500000","currency_code":"USD"},"quantity":1860}],"instrument_id":"4778aeb0-daf5-49fa-89e4-44603ebcee95","updated_at":"2023-01-05T19:13:13.660506737-05:00"}