{"asks":[{"side":"ask","price":{"amount":"0.610000","currency_code":"USD"},"quantity":100},{"side":"ask","price":{"amount":"0.640400","currency_code":"USD"},"quantity":100},{"side":"ask","price":{"amount":"0.643100","currency_code":"USD"},"quantity":100},{"side":"ask","price":{"amount":"0.710000","currency_code":"USD"},"quantity":141},{"side":"ask","price":{"amount":"0.780000","currency_code":"USD"},"quantity":129},{"side":"ask","price":{"amount":"0.860000","currency_code":"USD"},"quantity":117},{"side":"ask","price":{"amount":"0.940000","currency_code":"USD"},"quantity":107},{"side":"ask","price":{"amount":"0.972000","currency_code":"USD"},"quantity":85},{"side":"ask","price":{"amount":"1.080000","currency_code":"USD"},"quantity":1},{"side":"ask","price":{"amount":"1.500000","currency_code":"USD"},"quantity":1146},{"side":"ask","price":{"amount":"1.900000","currency_code":"USD"},"quantity":100},{"side":"ask","price":{"amount":"3.000000","currency_code":"USD"},"quantity":350},{"side":"ask","price":{"amount":"4.000000","currency_code":"USD"},"quantity":333},{"side":"ask","price":{"amount":"10.000000","currency_code":"USD"},"quantity":140},{"side":"ask","price":{"amount":"30.000000","currency_code":"USD"},"quantity":140}],"bids":[{"side":"bid","price":{"amount":"0.556000","currency_code":"USD"},"quantity":50},{"side":"bid","price":{"amount":"0.510000","currency_code":"USD"},"quantity":10},{"side":"bid","price":{"amount":"0.503000","currency_code":"USD"},"quantity":100},{"side":"bid","price":{"amount":"0.500500","currency_code":"USD"},"quantity":100},{"side":"bid","price":{"amount":"0.500000","currency_code":"USD"},"quantity":200},{"side":"bid","price":{"amount":"0.450000","currency_code":"USD"},"quantity":2222},{"side":"bid","price":{"amount":"0.380000","currency_code":"USD"},"quantity":6578}],"instrument_id":"70739dd8-78a7-4cda-9620-ca45bb1a2b10","updated_at":"2023-01-05T19:14:19.614681581-05:00"}