{"asks":[{"side":"ask","price":{"amount":"0.895000","currency_code":"USD"},"quantity":1500},{"side":"ask","price":{"amount":"0.899900","currency_code":"USD"},"quantity":500},{"side":"ask","price":{"amount":"0.900000","currency_code":"USD"},"quantity":100},{"side":"ask","price":{"amount":"0.905000","currency_code":"USD"},"quantity":1000},{"side":"ask","price":{"amount":"0.966000","currency_code":"USD"},"quantity":100},{"side":"ask","price":{"amount":"0.970100","currency_code":"USD"},"quantity":100},{"side":"ask","price":{"amount":"1.290000","currency_code":"USD"},"quantity":1000},{"side":"ask","price":{"amount":"2.000000","currency_code":"USD"},"quantity":100},{"side":"ask","price":{"amount":"2.600000","currency_code":"USD"},"quantity":100},{"side":"ask","price":{"amount":"3.300000","currency_code":"USD"},"quantity":100},{"side":"ask","price":{"amount":"4.800000","currency_code":"USD"},"quantity":100},{"side":"ask","price":{"amount":"6.000000","currency_code":"USD"},"quantity":100},{"side":"ask","price":{"amount":"7.100000","currency_code":"USD"},"quantity":100},{"side":"ask","price":{"amount":"8.250000","currency_code":"USD"},"quantity":100}],"bids":[{"side":"bid","price":{"amount":"0.860000","currency_code":"USD"},"quantity":500},{"side":"bid","price":{"amount":"0.800100","currency_code":"USD"},"quantity":2000},{"side":"bid","price":{"amount":"0.800000","currency_code":"USD"},"quantity":2500},{"side":"bid","price":{"amount":"0.795700","currency_code":"USD"},"quantity":100},{"side":"bid","price":{"amount":"0.791700","currency_code":"USD"},"quantity":100},{"side":"bid","price":{"amount":"0.752000","currency_code":"USD"},"quantity":2000}],"instrument_id":"be118c83-aa90-4aa8-8a24-5e34a26f5fec","updated_at":"2023-01-05T19:16:17.849787078-05:00"}